pytRIBS/__init__.py
pytRIBS/classes.py
pytRIBS/land/__init__.py
pytRIBS/land/land.py
pytRIBS/mesh/__init__.py
pytRIBS/mesh/mesh.py
pytRIBS/mesh/run_docker.py
pytRIBS/met/__init__.py
pytRIBS/met/met.py
pytRIBS/model/__init__.py
pytRIBS/model/model.py
pytRIBS/model/run_docker.py
pytRIBS/results/__init__.py
pytRIBS/results/evaluate.py
pytRIBS/results/read.py
pytRIBS/results/visualize.py
pytRIBS/results/waterbalance.py
pytRIBS/shared/__init__.py
pytRIBS/shared/aux.py
pytRIBS/shared/infile_mixin.py
pytRIBS/shared/inout.py
pytRIBS/shared/shared_mixin.py
pytRIBS/shared/color/__init__.py
pytRIBS/shared/color/tol_colors.py
pytRIBS/soil/__init__.py
pytRIBS/soil/soil.py
pytRIBS-0.5.0.dist-info/LICENSE
pytRIBS-0.5.0.dist-info/METADATA
pytRIBS-0.5.0.dist-info/WHEEL
pytRIBS-0.5.0.dist-info/top_level.txt
pytRIBS-0.5.0.dist-info/RECORD
