Metadata-Version: 2.1
Name: pytRIBS
Version: 0.5.0
Summary: A pre-to-post processing python package for the distributed hydrological model tRIBS
Author-email: "L. Wren Raming" <lraming@asu.edu>, "C. Josh Cederstrom" <cjceders@asu.edu>, "Enrique R. Vivoni" <evivoni@asu.edu>
License: GPL-version 2
Project-URL: Repository, https://github.com/tribshms/pytRIBS
Keywords: hydrology,modeling
License-File: LICENSE
Requires-Dist: numpy
Requires-Dist: pandas
Requires-Dist: matplotlib
Requires-Dist: geopandas
Requires-Dist: shapely
Requires-Dist: rasterio
Requires-Dist: scipy
Requires-Dist: rosetta-soil
Requires-Dist: owslib
Requires-Dist: matplotlib-scalebar
Requires-Dist: pynldas2
Requires-Dist: pyproj
Requires-Dist: xarray
Requires-Dist: requests
Requires-Dist: pyvista
Requires-Dist: whitebox
Requires-Dist: scikit-learn
Requires-Dist: PyWavelets
Requires-Dist: docker
Requires-Dist: timezonefinder
